eda/EDA.py
eda/__init__.py
eda/exploratory_data_analysis.py
eda-pandas/EDA.py
eda-pandas/__init__.py
eda_pandas-0.1.2.data/scripts/EDA.py
eda_pandas-0.1.2.data/scripts/__init__.py
eda_pandas-0.1.2.data/scripts/exploratory_data_analysis.py
eda_pandas-0.1.2.dist-info/METADATA
eda_pandas-0.1.2.dist-info/RECORD
eda_pandas-0.1.2.dist-info/WHEEL
eda_pandas-0.1.2.dist-info/top_level.txt
