Metadata-Version: 2.1
Name: eda-pandas
Version: 0.1.2
Summary: An Exploratory Data Analysis tool for pandas dataframe
Home-page: https://gist.github.com/jiahao87/c97214065f996b76ab8fe4ca1964b2b5
Author: jiahao87
License: MIT
Platform: UNKNOWN
Classifier: Programming Language :: Python :: 3
Classifier: License :: OSI Approved :: MIT License
Classifier: Operating System :: OS Independent
